arp_jarvis/__init__.py
arp_jarvis/auth.py
arp_jarvis/cli.py
arp_jarvis/compose.py
arp_jarvis/config.py
arp_jarvis/doctor.py
arp_jarvis/envfile.py
arp_jarvis/http_client.py
arp_jarvis/nodes.py
arp_jarvis/output.py
arp_jarvis/runs.py
arp_jarvis-0.3.8.dist-info/licenses/LICENSE
arp_jarvis-0.3.8.dist-info/METADATA
arp_jarvis-0.3.8.dist-info/WHEEL
arp_jarvis-0.3.8.dist-info/entry_points.txt
arp_jarvis-0.3.8.dist-info/top_level.txt
arp_jarvis-0.3.8.dist-info/RECORD
