Metadata-Version: 2.4
Name: arp-jarvis
Version: 0.3.8
Summary: Stack distribution that pins compatible JARVIS components.
Author: Agent Runtime Protocol
License-Expression: MIT
Project-URL: Repository, https://github.com/AgentRuntimeProtocol/JARVIS_Release
Project-URL: Issues, https://github.com/AgentRuntimeProtocol/JARVIS_Release/issues
Requires-Python: >=3.10
License-File: LICENSE
Requires-Dist: arp-jarvis-rungateway==0.3.8
Requires-Dist: arp-jarvis-run-coordinator==0.3.8
Requires-Dist: arp-jarvis-atomic-executor==0.3.8
Requires-Dist: arp-jarvis-composite-executor==0.3.8
Requires-Dist: arp-jarvis-node-registry==0.3.8
Requires-Dist: arp-jarvis-selection-service==0.3.8
Requires-Dist: arp-jarvis-pdp==0.3.8
Requires-Dist: arp-jarvis-runstore==0.3.8
Requires-Dist: arp-jarvis-eventstream==0.3.8
Requires-Dist: arp-jarvis-artifactstore==0.3.8
Requires-Dist: arp-jarvis-atomic-nodes==0.3.8
Dynamic: license-file
